apiarist/__init__.py
apiarist/conf.py
apiarist/emr.py
apiarist/job.py
apiarist/launch.py
apiarist/local.py
apiarist/s3.py
apiarist/script.py
apiarist/serde.py
apiarist/util.py
apiarist/jars/csv-serde-1.1.2-0.11.0-all.jar
apiarist-0.2.3.dist-info/LICENSE
apiarist-0.2.3.dist-info/METADATA
apiarist-0.2.3.dist-info/WHEEL
apiarist-0.2.3.dist-info/top_level.txt
apiarist-0.2.3.dist-info/RECORD
