Metadata-Version: 2.1
Name: apiarist
Version: 0.2.3
Summary: Python Hive query framework
Home-page: http://github.com/msharp/apiarist
Author: Max Sharples
Author-email: maxsharples@gmail.com
License: Apache
Platform: UNKNOWN
Classifier: Development Status :: 4 - Beta
Classifier: Intended Audience :: Developers
Classifier: License :: OSI Approved :: Apache Software License
Classifier: Natural Language :: English
Classifier: Operating System :: OS Independent
Classifier: Programming Language :: Python
Classifier: Programming Language :: Python :: 2.6
Classifier: Programming Language :: Python :: 2.7
Classifier: Programming Language :: Python :: 3.5
Classifier: Topic :: System :: Distributed Computing
Provides: apiarist
Requires-Dist: boto (>=2.6.0)
